{
  "modernCursive_meaning": [
    { "id": 1, "guess": "yod", "board": "Arm or Hand" },
    { "id": 2, "guess": "qoph", "board": "Back of Head" },
    { "id": 3, "guess": "gimel", "board": "Camel or Throwing Stick" },
    { "id": 4, "guess": "tau", "board": "Cross or Owner's Mark" },
    { "id": 5, "guess": "daleth", "board": "Door" },
    { "id": 6, "guess": "ayin", "board": "Eye" },
    { "id": 7, "guess": "cheth", "board": "Fence, Enclosure, or Courtyard" },
    { "id": 8, "guess": "nun", "board": "Fish" },
    { "id": 9, "guess": "tzaddi", "board": "Fish-hook or Plant" },
    { "id": 10, "guess": "resh", "board": "Head" },
    { "id": 11, "guess": "vau", "board": "Hook" },
    { "id": 12, "guess": "beth", "board": "House" },
    { "id": 13, "guess": "pe", "board": "Mouth" },
    { "id": 14, "guess": "lamed", "board": "Ox-Goad or Learn" },
    { "id": 15, "guess": "aleph", "board": "Ox-Head" },
    { "id": 16, "guess": "kaph", "board": "Palm" },
    { "id": 17, "guess": "samekh", "board": "Pillar or Support" },
    { "id": 18, "guess": "teth", "board": "Spindle" },
    { "id": 19, "guess": "shin", "board": "Tooth" },
    { "id": 20, "guess": "mem", "board": "Water" },
    { "id": 21, "guess": "zayin", "board": "Weapon" },
    { "id": 22, "guess": "he", "board": "Window" }
  ],
  "modernCursive_name": [
    { "id": 1, "guess": "aleph", "board": "Aleph" },
    { "id": 2, "guess": "beth", "board": "Beth" },
    { "id": 3, "guess": "gimel", "board": "Gimel" },
    { "id": 4, "guess": "daleth", "board": "Daleth" },
    { "id": 5, "guess": "he", "board": "He" },
    { "id": 6, "guess": "vau", "board": "Vau" },
    { "id": 7, "guess": "zayin", "board": "Zayin" },
    { "id": 8, "guess": "cheth", "board": "Cheth" },
    { "id": 9, "guess": "teth", "board": "Teth" },
    { "id": 10, "guess": "yod", "board": "Yod" },
    { "id": 11, "guess": "kaph", "board": "Kaph" },
    { "id": 12, "guess": "kaph-fin", "board": "Kaph Sofit" },
    { "id": 13, "guess": "lamed", "board": "Lamed" },
    { "id": 14, "guess": "mem", "board": "Mem" },
    { "id": 15, "guess": "mem-fin", "board": "Mem Sofit" },
    { "id": 16, "guess": "nun", "board": "Nun" },
    { "id": 17, "guess": "nun-fin", "board": "Nun Sofit" },
    { "id": 18, "guess": "samekh", "board": "Samekh" },
    { "id": 19, "guess": "ayin", "board": "Ayin" },
    { "id": 20, "guess": "pe", "board": "Pe" },
    { "id": 21, "guess": "pe-fin", "board": "Pe Sofit" },
    { "id": 22, "guess": "tzaddi", "board": "Tzaddi" },
    { "id": 23, "guess": "tzaddi-fin", "board": "Tzaddi Sofit" },
    { "id": 24, "guess": "qoph", "board": "Qoph" },
    { "id": 25, "guess": "resh", "board": "Resh" },
    { "id": 26, "guess": "shin", "board": "Shin" },
    { "id": 27, "guess": "tau", "board": "Tau" }
  ],
  "modernCursive_position": [
    { "id": 1, "guess": "aleph", "board": 1 },
    { "id": 2, "guess": "beth", "board": 2 },
    { "id": 3, "guess": "gimel", "board": 3 },
    { "id": 4, "guess": "daleth", "board": 4 },
    { "id": 5, "guess": "he", "board": 5 },
    { "id": 6, "guess": "vau", "board": 6 },
    { "id": 7, "guess": "zayin", "board": 7 },
    { "id": 8, "guess": "cheth", "board": 8 },
    { "id": 9, "guess": "teth", "board": 9 },
    { "id": 10, "guess": "yod", "board": 10 },
    { "id": 11, "guess": "kaph", "board": 11 },
    { "id": 12, "guess": "lamed", "board": 12 },
    { "id": 13, "guess": "mem", "board": 13 },
    { "id": 14, "guess": "nun", "board": 14 },
    { "id": 15, "guess": "samekh", "board": 15 },
    { "id": 16, "guess": "ayin", "board": 16 },
    { "id": 17, "guess": "pe", "board": 17 },
    { "id": 18, "guess": "tzaddi", "board": 18 },
    { "id": 19, "guess": "qoph", "board": 19 },
    { "id": 20, "guess": "resh", "board": 20 },
    { "id": 21, "guess": "shin", "board": 21 },
    { "id": 22, "guess": "tau", "board": 22 }
  ],
  "modernCursive_power": [
    { "id": 1, "guess": "aleph", "board": "A" },
    { "id": 2, "guess": "ayin", "board": "Aa, Ngh" },
    { "id": 3, "guess": "beth", "board": "B, V" },
    { "id": 4, "guess": "cheth", "board": "Ch" },
    { "id": 5, "guess": "daleth", "board": "D, Dh" },
    { "id": 6, "guess": "gimel", "board": "G, Gh" },
    { "id": 7, "guess": "he", "board": "H" },
    { "id": 8, "guess": "yod", "board": "I, Y" },
    { "id": 9, "guess": "kaph", "board": "K, Kh" },
    { "id": 10, "guess": "lamed", "board": "L" },
    { "id": 11, "guess": "mem", "board": "M" },
    { "id": 12, "guess": "nun", "board": "N" },
    { "id": 13, "guess": "vau", "board": "O, U, V" },
    { "id": 14, "guess": "pe", "board": "P, Ph" },
    { "id": 15, "guess": "qoph", "board": "Q" },
    { "id": 16, "guess": "resh", "board": "R" },
    { "id": 17, "guess": "samekh", "board": "S" },
    { "id": 18, "guess": "shin", "board": "S, Sh" },
    { "id": 19, "guess": "teth", "board": "T" },
    { "id": 20, "guess": "tau", "board": "T, Th" },
    { "id": 21, "guess": "tzaddi", "board": "Tz" },
    { "id": 22, "guess": "zayin", "board": "Z" }
  ],
  "modernCursive_pronunciation": [
    { "id": 1, "guess": "aleph", "board": "silent" },
    { "id": 2, "guess": "ayin", "board": "silent" },
    { "id": 3, "guess": "beth", "board": "b or v" },
    { "id": 4, "guess": "cheth", "board": "ch" },
    { "id": 5, "guess": "daleth", "board": "d" },
    { "id": 6, "guess": "gimel", "board": "g" },
    { "id": 7, "guess": "he", "board": "h" },
    { "id": 8, "guess": "kaph", "board": "k or kh" },
    { "id": 9, "guess": "lamed", "board": "l" },
    { "id": 10, "guess": "mem", "board": "m" },
    { "id": 11, "guess": "nun", "board": "n" },
    { "id": 12, "guess": "pe", "board": "p or f/ph" },
    { "id": 13, "guess": "qoph", "board": "q" },
    { "id": 14, "guess": "resh", "board": "r" },
    { "id": 15, "guess": "samekh", "board": "s" },
    { "id": 16, "guess": "shin", "board": "s or sh" },
    { "id": 17, "guess": "teth", "board": "t" },
    { "id": 18, "guess": "tau", "board": "t or th" },
    { "id": 19, "guess": "tzaddi", "board": "ts" },
    { "id": 20, "guess": "vau", "board": "v or w" },
    { "id": 21, "guess": "yod", "board": "y" },
    { "id": 22, "guess": "zayin", "board": "z" }
  ],
  "modernCursive_transliteration": [
    { "id": 1, "guess": "aleph", "board": "Ê¾" },
    { "id": 2, "guess": "ayin", "board": "Ê¿" },
    { "id": 3, "guess": "beth", "board": "b or á¸‡" },
    { "id": 4, "guess": "daleth", "board": "d or á¸" },
    { "id": 5, "guess": "gimel", "board": "g or á¸¡" },
    { "id": 6, "guess": "he", "board": "h" },
    { "id": 7, "guess": "cheth", "board": "á¸¥" },
    { "id": 8, "guess": "kaph", "board": "k or á¸µ" },
    { "id": 9, "guess": "lamed", "board": "l" },
    { "id": 10, "guess": "mem", "board": "m" },
    { "id": 11, "guess": "nun", "board": "n" },
    { "id": 12, "guess": "pe", "board": "p or pÌ„" },
    { "id": 13, "guess": "qoph", "board": "q" },
    { "id": 14, "guess": "resh", "board": "r" },
    { "id": 15, "guess": "samekh", "board": "s" },
    { "id": 16, "guess": "shin", "board": "Å› or Å¡" },
    { "id": 17, "guess": "tzaddi", "board": "á¹£" },
    { "id": 18, "guess": "tau", "board": "t or á¹¯" },
    { "id": 19, "guess": "teth", "board": "á¹­" },
    { "id": 20, "guess": "vau", "board": "v or w" },
    { "id": 21, "guess": "yod", "board": "y" },
    { "id": 22, "guess": "zayin", "board": "z" }
  ],
  "modernCursive_value": [
    { "id": 1, "guess": "aleph", "board": 1 },
    { "id": 2, "guess": "beth", "board": 2 },
    { "id": 3, "guess": "gimel", "board": 3 },
    { "id": 4, "guess": "daleth", "board": 4 },
    { "id": 5, "guess": "he", "board": 5 },
    { "id": 6, "guess": "vau", "board": 6 },
    { "id": 7, "guess": "zayin", "board": 7 },
    { "id": 8, "guess": "cheth", "board": 8 },
    { "id": 9, "guess": "teth", "board": 9 },
    { "id": 10, "guess": "yod", "board": 10 },
    { "id": 11, "guess": "kaph", "board": 20 },
    { "id": 12, "guess": "lamed", "board": 30 },
    { "id": 13, "guess": "mem", "board": 40 },
    { "id": 14, "guess": "nun", "board": 50 },
    { "id": 15, "guess": "samekh", "board": 60 },
    { "id": 16, "guess": "ayin", "board": 70 },
    { "id": 17, "guess": "pe", "board": 80 },
    { "id": 18, "guess": "tzaddi", "board": 90 },
    { "id": 19, "guess": "qoph", "board": 100 },
    { "id": 20, "guess": "resh", "board": 200 },
    { "id": 21, "guess": "shin", "board": 300 },
    { "id": 22, "guess": "tau", "board": 400 },
    { "id": 23, "guess": "kaph-fin", "board": 500 },
    { "id": 24, "guess": "mem-fin", "board": 600 },
    { "id": 25, "guess": "nun-fin", "board": 700 },
    { "id": 26, "guess": "pe-fin", "board": 800 },
    { "id": 27, "guess": "tzaddi-fin", "board": 900 }
  ],
  "paleoHebrew_meaning": [
    { "id": 1, "guess": "ğ¤‰", "board": "Arm or Hand" },
    { "id": 2, "guess": "ğ¤’", "board": "Back of Head" },
    { "id": 3, "guess": "ğ¤‚", "board": "Camel or Throwing Stick" },
    { "id": 4, "guess": "ğ¤•", "board": "Cross or Owner's Mark" },
    { "id": 5, "guess": "ğ¤ƒ", "board": "Door" },
    { "id": 6, "guess": "ğ¤", "board": "Eye" },
    { "id": 7, "guess": "ğ¤‡", "board": "Fence, Enclosure, or Courtyard" },
    { "id": 8, "guess": "ğ¤", "board": "Fish" },
    { "id": 9, "guess": "ğ¤‘", "board": "Fish-hook or Plant" },
    { "id": 10, "guess": "ğ¤“", "board": "Head" },
    { "id": 11, "guess": "ğ¤…", "board": "Hook" },
    { "id": 12, "guess": "ğ¤", "board": "House" },
    { "id": 13, "guess": "ğ¤", "board": "Mouth" },
    { "id": 14, "guess": "ğ¤‹", "board": "Ox-Goad or Learn" },
    { "id": 15, "guess": "ğ¤€", "board": "Ox-Head" },
    { "id": 16, "guess": "ğ¤Š", "board": "Palm" },
    { "id": 17, "guess": "ğ¤", "board": "Pillar or Support" },
    { "id": 18, "guess": "ğ¤ˆ", "board": "Spindle" },
    { "id": 19, "guess": "ğ¤”", "board": "Tooth" },
    { "id": 20, "guess": "ğ¤Œ", "board": "Water" },
    { "id": 21, "guess": "ğ¤†", "board": "Weapon" },
    { "id": 22, "guess": "ğ¤„", "board": "Window" }
  ],
  "paleoHebrew_name": [
    { "id": 1, "guess": "ğ¤€", "board": "Aleph" },
    { "id": 2, "guess": "ğ¤", "board": "Beth" },
    { "id": 3, "guess": "ğ¤‚", "board": "Gimel" },
    { "id": 4, "guess": "ğ¤ƒ", "board": "Daleth" },
    { "id": 5, "guess": "ğ¤„", "board": "He" },
    { "id": 6, "guess": "ğ¤…", "board": "Vau" },
    { "id": 7, "guess": "ğ¤†", "board": "Zayin" },
    { "id": 8, "guess": "ğ¤‡", "board": "Cheth" },
    { "id": 9, "guess": "ğ¤ˆ", "board": "Teth" },
    { "id": 10, "guess": "ğ¤‰", "board": "Yod" },
    { "id": 11, "guess": "ğ¤Š", "board": "Kaph" },
    { "id": 12, "guess": "ğ¤‹", "board": "Lamed" },
    { "id": 13, "guess": "ğ¤Œ", "board": "Mem" },
    { "id": 14, "guess": "ğ¤", "board": "Nun" },
    { "id": 15, "guess": "ğ¤", "board": "Samekh" },
    { "id": 16, "guess": "ğ¤", "board": "Ayin" },
    { "id": 17, "guess": "ğ¤", "board": "Pe" },
    { "id": 18, "guess": "ğ¤‘", "board": "Tzaddi" },
    { "id": 19, "guess": "ğ¤’", "board": "Qoph" },
    { "id": 20, "guess": "ğ¤“", "board": "Resh" },
    { "id": 21, "guess": "ğ¤”", "board": "Shin" },
    { "id": 22, "guess": "ğ¤•", "board": "Tau" }
  ],
  "paleoHebrew_position": [
    { "id": 1, "guess": "ğ¤€", "board": 1 },
    { "id": 2, "guess": "ğ¤", "board": 2 },
    { "id": 3, "guess": "ğ¤‚", "board": 3 },
    { "id": 4, "guess": "ğ¤ƒ", "board": 4 },
    { "id": 5, "guess": "ğ¤„", "board": 5 },
    { "id": 6, "guess": "ğ¤…", "board": 6 },
    { "id": 7, "guess": "ğ¤†", "board": 7 },
    { "id": 8, "guess": "ğ¤‡", "board": 8 },
    { "id": 9, "guess": "ğ¤ˆ", "board": 9 },
    { "id": 10, "guess": "ğ¤‰", "board": 10 },
    { "id": 11, "guess": "ğ¤Š", "board": 11 },
    { "id": 12, "guess": "ğ¤‹", "board": 12 },
    { "id": 13, "guess": "ğ¤Œ", "board": 13 },
    { "id": 14, "guess": "ğ¤", "board": 14 },
    { "id": 15, "guess": "ğ¤", "board": 15 },
    { "id": 16, "guess": "ğ¤", "board": 16 },
    { "id": 17, "guess": "ğ¤", "board": 17 },
    { "id": 18, "guess": "ğ¤‘", "board": 18 },
    { "id": 19, "guess": "ğ¤’", "board": 19 },
    { "id": 20, "guess": "ğ¤“", "board": 20 },
    { "id": 21, "guess": "ğ¤”", "board": 21 },
    { "id": 22, "guess": "ğ¤•", "board": 22 }
  ],
  "paleoHebrew_power": [
    { "id": 1, "guess": "ğ¤€", "board": "A" },
    { "id": 2, "guess": "ğ¤", "board": "Aa, Ngh" },
    { "id": 3, "guess": "ğ¤", "board": "B, V" },
    { "id": 4, "guess": "ğ¤‡", "board": "Ch" },
    { "id": 5, "guess": "ğ¤ƒ", "board": "D, Dh" },
    { "id": 6, "guess": "ğ¤‚", "board": "G, Gh" },
    { "id": 7, "guess": "ğ¤„", "board": "H" },
    { "id": 8, "guess": "ğ¤‰", "board": "I, Y" },
    { "id": 9, "guess": "ğ¤Š", "board": "K, Kh" },
    { "id": 10, "guess": "ğ¤‹", "board": "L" },
    { "id": 11, "guess": "ğ¤Œ", "board": "M" },
    { "id": 12, "guess": "ğ¤", "board": "N" },
    { "id": 13, "guess": "ğ¤…", "board": "O, U, V" },
    { "id": 14, "guess": "ğ¤", "board": "P, Ph" },
    { "id": 15, "guess": "ğ¤’", "board": "Q" },
    { "id": 16, "guess": "ğ¤“", "board": "R" },
    { "id": 17, "guess": "ğ¤", "board": "S" },
    { "id": 18, "guess": "ğ¤”", "board": "S, Sh" },
    { "id": 19, "guess": "ğ¤ˆ", "board": "T" },
    { "id": 20, "guess": "ğ¤•", "board": "T, Th" },
    { "id": 21, "guess": "ğ¤‘", "board": "Tz" },
    { "id": 22, "guess": "ğ¤†", "board": "Z" }
  ],
  "paleoHebrew_pronunciation": [
    { "id": 1, "guess": "ğ¤€", "board": "silent" },
    { "id": 1, "guess": "ğ¤", "board": "silent" },
    { "id": 2, "guess": "ğ¤", "board": "b or v" },
    { "id": 3, "guess": "ğ¤‡", "board": "ch" },
    { "id": 4, "guess": "ğ¤ƒ", "board": "d" },
    { "id": 5, "guess": "ğ¤‚", "board": "g" },
    { "id": 6, "guess": "ğ¤„", "board": "h" },
    { "id": 7, "guess": "ğ¤Š", "board": "k or kh" },
    { "id": 8, "guess": "ğ¤‹", "board": "l" },
    { "id": 9, "guess": "ğ¤Œ", "board": "m" },
    { "id": 10, "guess": "ğ¤", "board": "n" },
    { "id": 11, "guess": "ğ¤", "board": "p of f/ph" },
    { "id": 12, "guess": "ğ¤’", "board": "q" },
    { "id": 13, "guess": "ğ¤“", "board": "r" },
    { "id": 14, "guess": "ğ¤", "board": "s" },
    { "id": 15, "guess": "ğ¤”", "board": "s or sh" },
    { "id": 16, "guess": "ğ¤ˆ", "board": "t" },
    { "id": 17, "guess": "ğ¤•", "board": "t or th" },
    { "id": 18, "guess": "ğ¤‘", "board": "ts" },
    { "id": 19, "guess": "ğ¤…", "board": "v or w" },
    { "id": 20, "guess": "ğ¤‰", "board": "y" },
    { "id": 21, "guess": "ğ¤†", "board": "z" }
  ],
  "paleoHebrew_transliteration": [
    { "id": 1, "guess": "ğ¤€", "board": "Ê¾" },
    { "id": 2, "guess": "ğ¤", "board": "Ê¿" },
    { "id": 3, "guess": "ğ¤", "board": "b or á¸‡" },
    { "id": 4, "guess": "ğ¤ƒ", "board": "d or á¸" },
    { "id": 5, "guess": "ğ¤‚", "board": "g or á¸¡" },
    { "id": 6, "guess": "ğ¤„", "board": "h" },
    { "id": 7, "guess": "ğ¤‡", "board": "á¸¥" },
    { "id": 8, "guess": "ğ¤Š", "board": "k or á¸µ" },
    { "id": 9, "guess": "ğ¤‹", "board": "l" },
    { "id": 10, "guess": "ğ¤Œ", "board": "m" },
    { "id": 11, "guess": "ğ¤", "board": "n" },
    { "id": 12, "guess": "ğ¤", "board": "p or pÌ„" },
    { "id": 13, "guess": "ğ¤’", "board": "q" },
    { "id": 14, "guess": "ğ¤“", "board": "r" },
    { "id": 15, "guess": "ğ¤", "board": "s" },
    { "id": 16, "guess": "ğ¤”", "board": "Å› or Å¡" },
    { "id": 17, "guess": "ğ¤‘", "board": "á¹£" },
    { "id": 18, "guess": "ğ¤•", "board": "t or á¹¯" },
    { "id": 19, "guess": "ğ¤ˆ", "board": "á¹­" },
    { "id": 20, "guess": "ğ¤…", "board": "v or w" },
    { "id": 21, "guess": "ğ¤‰", "board": "y" },
    { "id": 22, "guess": "ğ¤†", "board": "z" }
  ],
  "paleoHebrew_value": [
    { "id": 1, "guess": "ğ¤€", "board": 1 },
    { "id": 2, "guess": "ğ¤", "board": 2 },
    { "id": 3, "guess": "ğ¤‚", "board": 3 },
    { "id": 4, "guess": "ğ¤ƒ", "board": 4 },
    { "id": 5, "guess": "ğ¤„", "board": 5 },
    { "id": 6, "guess": "ğ¤…", "board": 6 },
    { "id": 7, "guess": "ğ¤†", "board": 7 },
    { "id": 8, "guess": "ğ¤‡", "board": 8 },
    { "id": 9, "guess": "ğ¤ˆ", "board": 9 },
    { "id": 10, "guess": "ğ¤‰", "board": 10 },
    { "id": 11, "guess": "ğ¤Š", "board": 20 },
    { "id": 12, "guess": "ğ¤‹", "board": 30 },
    { "id": 13, "guess": "ğ¤Œ", "board": 40 },
    { "id": 14, "guess": "ğ¤", "board": 50 },
    { "id": 15, "guess": "ğ¤", "board": 60 },
    { "id": 16, "guess": "ğ¤", "board": 70 },
    { "id": 17, "guess": "ğ¤", "board": 80 },
    { "id": 18, "guess": "ğ¤‘", "board": 90 },
    { "id": 19, "guess": "ğ¤’", "board": 100 },
    { "id": 20, "guess": "ğ¤“", "board": 200 },
    { "id": 21, "guess": "ğ¤”", "board": 300 },
    { "id": 22, "guess": "ğ¤•", "board": 400 }
  ],
  "unicode_meaning": [
    { "id": 1, "guess": "&#1497;", "board": "Arm or Hand" },
    { "id": 2, "guess": "&#1511;", "board": "Back of Head" },
    { "id": 3, "guess": "&#1490;", "board": "Camel or Throwing Stick" },
    { "id": 4, "guess": "&#1514;", "board": "Cross or Owner's Mark" },
    { "id": 5, "guess": "&#1491;", "board": "Door" },
    { "id": 6, "guess": "&#1506;", "board": "Eye" },
    { "id": 7, "guess": "&#1495;", "board": "Fence, Enclosure, or Courtyard" },
    { "id": 8, "guess": "&#1504;", "board": "Fish" },
    { "id": 9, "guess": "&#1510;", "board": "Fish-hook or Plant" },
    { "id": 10, "guess": "&#1512;", "board": "Head" },
    { "id": 11, "guess": "&#1493;", "board": "Hook" },
    { "id": 12, "guess": "&#1489;", "board": "House" },
    { "id": 13, "guess": "&#1508;", "board": "Mouth" },
    { "id": 14, "guess": "&#1500;", "board": "Ox-Goad or Learn" },
    { "id": 15, "guess": "&#1488;", "board": "Ox-Head" },
    { "id": 16, "guess": "&#1499;", "board": "Palm" },
    { "id": 17, "guess": "&#1505;", "board": "Pillar or Support" },
    { "id": 18, "guess": "&#1496;", "board": "Spindle" },
    { "id": 19, "guess": "&#1513;", "board": "Tooth" },
    { "id": 20, "guess": "&#1502;", "board": "Water" },
    { "id": 21, "guess": "&#1494;", "board": "Weapon" },
    { "id": 22, "guess": "&#1492;", "board": "Window" }
  ],
  "unicode_name": [
    { "id": 1, "guess": "&#1488;", "board": "Aleph" },
    { "id": 2, "guess": "&#1489;", "board": "Beth" },
    { "id": 3, "guess": "&#1490;", "board": "Gimel" },
    { "id": 4, "guess": "&#1491;", "board": "Daleth" },
    { "id": 5, "guess": "&#1492;", "board": "He" },
    { "id": 6, "guess": "&#1493;", "board": "Vau" },
    { "id": 7, "guess": "&#1494;", "board": "Zayin" },
    { "id": 8, "guess": "&#1495;", "board": "Cheth" },
    { "id": 9, "guess": "&#1496;", "board": "Teth" },
    { "id": 10, "guess": "&#1497;", "board": "Yod" },
    { "id": 11, "guess": "&#1499;", "board": "Kaph" },
    { "id": 12, "guess": "&#1498;", "board": "Kaph Sofit" },
    { "id": 13, "guess": "&#1500;", "board": "Lamed" },
    { "id": 14, "guess": "&#1502;", "board": "Mem" },
    { "id": 15, "guess": "&#1501;", "board": "Mem Sofit" },
    { "id": 16, "guess": "&#1504;", "board": "Nun" },
    { "id": 17, "guess": "&#1503;", "board": "Nun Sofit" },
    { "id": 18, "guess": "&#1505;", "board": "Samekh" },
    { "id": 19, "guess": "&#1506;", "board": "Ayin" },
    { "id": 20, "guess": "&#1508;", "board": "Pe" },
    { "id": 21, "guess": "&#1507;", "board": "Pe Sofit" },
    { "id": 22, "guess": "&#1510;", "board": "Tzaddi" },
    { "id": 23, "guess": "&#1509;", "board": "Tzaddi Sofit" },
    { "id": 24, "guess": "&#1511;", "board": "Qoph" },
    { "id": 25, "guess": "&#1512;", "board": "Resh" },
    { "id": 26, "guess": "&#1513;&#1474;", "board": "Sin" },
    { "id": 27, "guess": "&#1513;&#1473;", "board": "Shin" },
    { "id": 28, "guess": "&#1514;", "board": "Tau" }
  ],
  "unicode_position": [
    { "id": 1, "guess": "&#1488;", "board": 1 },
    { "id": 2, "guess": "&#1489;", "board": 2 },
    { "id": 3, "guess": "&#1490;", "board": 3 },
    { "id": 4, "guess": "&#1491;", "board": 4 },
    { "id": 5, "guess": "&#1492;", "board": 5 },
    { "id": 6, "guess": "&#1493;", "board": 6 },
    { "id": 7, "guess": "&#1494;", "board": 7 },
    { "id": 8, "guess": "&#1495;", "board": 8 },
    { "id": 9, "guess": "&#1496;", "board": 9 },
    { "id": 10, "guess": "&#1497;", "board": 10 },
    { "id": 11, "guess": "&#1499;", "board": 11 },
    { "id": 11, "guess": "&#1498;", "board": 11 },
    { "id": 12, "guess": "&#1500;", "board": 12 },
    { "id": 13, "guess": "&#1502;", "board": 13 },
    { "id": 13, "guess": "&#1501;", "board": 13 },
    { "id": 14, "guess": "&#1504;", "board": 14 },
    { "id": 14, "guess": "&#1503;", "board": 14 },
    { "id": 15, "guess": "&#1505;", "board": 15 },
    { "id": 16, "guess": "&#1506;", "board": 16 },
    { "id": 17, "guess": "&#1508;", "board": 17 },
    { "id": 17, "guess": "&#1507;", "board": 17 },
    { "id": 18, "guess": "&#1510;", "board": 18 },
    { "id": 18, "guess": "&#1509;", "board": 18 },
    { "id": 19, "guess": "&#1511;", "board": 19 },
    { "id": 20, "guess": "&#1512;", "board": 20 },
    { "id": 21, "guess": "&#1513;", "board": 21 },
    { "id": 22, "guess": "&#1514;", "board": 22 }
  ],
  "unicode_power": [
    { "id": 1, "guess": "&#1488;", "board": "A" },
    { "id": 2, "guess": "&#1506;", "board": "Aa, Ngh" },
    { "id": 3, "guess": "&#1489;&#1468;", "board": "B" },
    { "id": 4, "guess": "&#1495;", "board": "Ch" },
    { "id": 5, "guess": "&#1491;&#1468;", "board": "D" },
    { "id": 6, "guess": "&#1491;", "board": "Dh" },
    { "id": 7, "guess": "&#1490;&#1468;", "board": "G" },
    { "id": 8, "guess": "&#1490;", "board": "Gh" },
    { "id": 9, "guess": "&#1492;", "board": "H" },
    { "id": 10, "guess": "&#1497;", "board": "I, Y" },
    { "id": 11, "guess": "&#1499;&#1468;", "board": "K" },
    { "id": 11, "guess": "&#1498;&#1468;", "board": "K" },
    { "id": 12, "guess": "&#1499;", "board": "Kh" },
    { "id": 12, "guess": "&#1498;", "board": "Kh" },
    { "id": 13, "guess": "&#1500;", "board": "L" },
    { "id": 14, "guess": "&#1502;", "board": "M" },
    { "id": 14, "guess": "&#1501;", "board": "M" },
    { "id": 15, "guess": "&#1504;", "board": "N" },
    { "id": 15, "guess": "&#1503;", "board": "N" },
    { "id": 16, "guess": "&#1493;", "board": "O, U, V" },
    { "id": 17, "guess": "&#1508;&#1468;", "board": "P" },
    { "id": 17, "guess": "&#1507;&#1468;", "board": "P" },
    { "id": 18, "guess": "&#1508;", "board": "Ph" },
    { "id": 18, "guess": "&#1507;", "board": "Ph" },
    { "id": 19, "guess": "&#1511;", "board": "Q" },
    { "id": 20, "guess": "&#1512;", "board": "R" },
    { "id": 21, "guess": "&#1505;", "board": "S" },
    { "id": 21, "guess": "&#1513;&#1474;", "board": "S" },
    { "id": 22, "guess": "&#1513;&#1473;", "board": "Sh" },
    { "id": 23, "guess": "&#1496;", "board": "T" },
    { "id": 23, "guess": "&#1514;&#1468;", "board": "T" },
    { "id": 24, "guess": "&#1514;", "board": "Th" },
    { "id": 25, "guess": "&#1510;", "board": "Tz" },
    { "id": 25, "guess": "&#1509;", "board": "Tz" },
    { "id": 26, "guess": "&#1489;", "board": "V" },
    { "id": 27, "guess": "&#1494;", "board": "Z" }
  ],
  "unicode_pronunciation": [
    { "id": 1, "guess": "&#1488;", "board": "silent" },
    { "id": 1, "guess": "&#1506;", "board": "silent" },
    { "id": 2, "guess": "&#1489;&#1468;", "board": "b" },
    { "id": 3, "guess": "&#1495;", "board": "ch" },
    { "id": 4, "guess": "&#1491;", "board": "d" },
    { "id": 4, "guess": "&#1491;&#1468;", "board": "d" },
    { "id": 5, "guess": "&#1508;", "board": "f/ph" },
    { "id": 5, "guess": "&#1507;", "board": "f/ph" },
    { "id": 6, "guess": "&#1490;", "board": "g" },
    { "id": 6, "guess": "&#1490;&#1468;", "board": "g" },
    { "id": 7, "guess": "&#1492;", "board": "h" },
    { "id": 8, "guess": "&#1499;&#1468;", "board": "k" },
    { "id": 8, "guess": "&#1498;&#1468;", "board": "k" },
    { "id": 9, "guess": "&#1499;", "board": "kh" },
    { "id": 9, "guess": "&#1498;", "board": "kh" },
    { "id": 10, "guess": "&#1500;", "board": "l" },
    { "id": 11, "guess": "&#1502;", "board": "m" },
    { "id": 11, "guess": "&#1501;", "board": "m" },
    { "id": 12, "guess": "&#1504;", "board": "n" },
    { "id": 12, "guess": "&#1503;", "board": "n" },
    { "id": 13, "guess": "&#1508;&#1468;", "board": "p" },
    { "id": 13, "guess": "&#1507;&#1468;", "board": "p" },
    { "id": 14, "guess": "&#1511;", "board": "q" },
    { "id": 15, "guess": "&#1512;", "board": "r" },
    { "id": 16, "guess": "&#1505;", "board": "s" },
    { "id": 16, "guess": "&#1513;&#1474;", "board": "s" },
    { "id": 17, "guess": "&#1513;&#1473;", "board": "sh" },
    { "id": 18, "guess": "&#1496;", "board": "t" },
    { "id": 18, "guess": "&#1514;&#1468;", "board": "t" },
    { "id": 19, "guess": "&#1514;", "board": "th" },
    { "id": 20, "guess": "&#1510;", "board": "ts" },
    { "id": 20, "guess": "&#1509;", "board": "ts" },
    { "id": 21, "guess": "&#1489;", "board": "v" },
    { "id": 22, "guess": "&#1493;", "board": "v or w" },
    { "id": 23, "guess": "&#1497;", "board": "y" },
    { "id": 24, "guess": "&#1494;", "board": "z" }
  ],
  "unicode_transliteration": [
    { "id": 1, "guess": "&#1488;", "board": "Ê¾" },
    { "id": 2, "guess": "&#1506;", "board": "Ê¿" },
    { "id": 3, "guess": "&#1489;&#1468;", "board": "b" },
    { "id": 4, "guess": "&#1489;", "board": "á¸‡" },
    { "id": 5, "guess": "&#1491;&#1468;", "board": "d" },
    { "id": 6, "guess": "&#1491;", "board": "á¸" },
    { "id": 7, "guess": "&#1490;&#1468;", "board": "g" },
    { "id": 8, "guess": "&#1490;", "board": "á¸¡" },
    { "id": 9, "guess": "&#1492;", "board": "h" },
    { "id": 10, "guess": "&#1495;", "board": "á¸¥" },
    { "id": 11, "guess": "&#1499;&#1468;", "board": "k" },
    { "id": 11, "guess": "&#1498;&#1468;", "board": "k" },
    { "id": 12, "guess": "&#1499;", "board": "á¸µ" },
    { "id": 12, "guess": "&#1498;", "board": "á¸µ" },
    { "id": 13, "guess": "&#1500;", "board": "l" },
    { "id": 14, "guess": "&#1502;", "board": "m" },
    { "id": 14, "guess": "&#1501;", "board": "m" },
    { "id": 15, "guess": "&#1504;", "board": "n" },
    { "id": 15, "guess": "&#1503;", "board": "n" },
    { "id": 16, "guess": "&#1508;&#1468;", "board": "p" },
    { "id": 16, "guess": "&#1507;&#1468;", "board": "p" },
    { "id": 17, "guess": "&#1508;", "board": "pÌ„" },
    { "id": 17, "guess": "&#1507;", "board": "pÌ„" },
    { "id": 18, "guess": "&#1511;", "board": "q" },
    { "id": 19, "guess": "&#1512;", "board": "r" },
    { "id": 20, "guess": "&#1505;", "board": "s" },
    { "id": 21, "guess": "&#1513;&#1474;", "board": "Å›" },
    { "id": 22, "guess": "&#1513;&#1473;", "board": "Å¡" },
    { "id": 23, "guess": "&#1510;", "board": "á¹£" },
    { "id": 23, "guess": "&#1509;", "board": "á¹£" },
    { "id": 24, "guess": "&#1514;&#1468;", "board": "t" },
    { "id": 25, "guess": "&#1496;", "board": "á¹­" },
    { "id": 26, "guess": "&#1514;", "board": "á¹¯" },
    { "id": 27, "guess": "&#1493;", "board": "v or w" },
    { "id": 28, "guess": "&#1497;", "board": "y" },
    { "id": 29, "guess": "&#1494;", "board": "z" }
  ],
  "unicode_value": [
    { "id": 1, "guess": "&#1488;", "board": 1 },
    { "id": 2, "guess": "&#1489;", "board": 2 },
    { "id": 3, "guess": "&#1490;", "board": 3 },
    { "id": 4, "guess": "&#1491;", "board": 4 },
    { "id": 5, "guess": "&#1492;", "board": 5 },
    { "id": 6, "guess": "&#1493;", "board": 6 },
    { "id": 7, "guess": "&#1494;", "board": 7 },
    { "id": 8, "guess": "&#1495;", "board": 8 },
    { "id": 9, "guess": "&#1496;", "board": 9 },
    { "id": 10, "guess": "&#1497;", "board": 10 },
    { "id": 11, "guess": "&#1499;", "board": 20 },
    { "id": 12, "guess": "&#1500;", "board": 30 },
    { "id": 13, "guess": "&#1502;", "board": 40 },
    { "id": 14, "guess": "&#1504;", "board": 50 },
    { "id": 15, "guess": "&#1505;", "board": 60 },
    { "id": 16, "guess": "&#1506;", "board": 70 },
    { "id": 17, "guess": "&#1508;", "board": 80 },
    { "id": 18, "guess": "&#1510;", "board": 90 },
    { "id": 19, "guess": "&#1511;", "board": 100 },
    { "id": 20, "guess": "&#1512;", "board": 200 },
    { "id": 21, "guess": "&#1513;", "board": 300 },
    { "id": 22, "guess": "&#1514;", "board": 400 },
    { "id": 23, "guess": "&#1498;", "board": 500 },
    { "id": 24, "guess": "&#1501;", "board": 600 },
    { "id": 25, "guess": "&#1503;", "board": 700 },
    { "id": 26, "guess": "&#1507;", "board": 800 },
    { "id": 27, "guess": "&#1509;", "board": 900 }
  ]
}
